[
  {
    "LibraryStoryGroupingId": 500,
    "EventQuestChapterId": 500,
    "SortOrder": 1
  },
  {
    "LibraryStoryGroupingId": 500,
    "EventQuestChapterId": 510,
    "SortOrder": 1
  },
  {
    "LibraryStoryGroupingId": 501,
    "EventQuestChapterId": 501,
    "SortOrder": 2
  },
  {
    "LibraryStoryGroupingId": 502,
    "EventQuestChapterId": 502,
    "SortOrder": 3
  },
  {
    "LibraryStoryGroupingId": 503,
    "EventQuestChapterId": 503,
    "SortOrder": 4
  },
  {
    "LibraryStoryGroupingId": 505,
    "EventQuestChapterId": 505,
    "SortOrder": 6
  },
  {
    "LibraryStoryGroupingId": 506,
    "EventQuestChapterId": 506,
    "SortOrder": 5
  },
  {
    "LibraryStoryGroupingId": 507,
    "EventQuestChapterId": 507,
    "SortOrder": 7
  },
  {
    "LibraryStoryGroupingId": 508,
    "EventQuestChapterId": 508,
    "SortOrder": 8
  },
  {
    "LibraryStoryGroupingId": 509,
    "EventQuestChapterId": 509,
    "SortOrder": 10
  },
  {
    "LibraryStoryGroupingId": 511,
    "EventQuestChapterId": 511,
    "SortOrder": 9
  },
  {
    "LibraryStoryGroupingId": 512,
    "EventQuestChapterId": 512,
    "SortOrder": 12
  },
  {
    "LibraryStoryGroupingId": 512,
    "EventQuestChapterId": 584,
    "SortOrder": 12
  },
  {
    "LibraryStoryGroupingId": 513,
    "EventQuestChapterId": 513,
    "SortOrder": 11
  },
  {
    "LibraryStoryGroupingId": 514,
    "EventQuestChapterId": 514,
    "SortOrder": 13
  },
  {
    "LibraryStoryGroupingId": 515,
    "EventQuestChapterId": 515,
    "SortOrder": 14
  },
  {
    "LibraryStoryGroupingId": 517,
    "EventQuestChapterId": 517,
    "SortOrder": 15
  },
  {
    "LibraryStoryGroupingId": 519,
    "EventQuestChapterId": 519,
    "SortOrder": 16
  },
  {
    "LibraryStoryGroupingId": 521,
    "EventQuestChapterId": 521,
    "SortOrder": 17
  },
  {
    "LibraryStoryGroupingId": 522,
    "EventQuestChapterId": 522,
    "SortOrder": 18
  },
  {
    "LibraryStoryGroupingId": 522,
    "EventQuestChapterId": 585,
    "SortOrder": 18
  },
  {
    "LibraryStoryGroupingId": 524,
    "EventQuestChapterId": 524,
    "SortOrder": 19
  },
  {
    "LibraryStoryGroupingId": 526,
    "EventQuestChapterId": 526,
    "SortOrder": 21
  },
  {
    "LibraryStoryGroupingId": 527,
    "EventQuestChapterId": 527,
    "SortOrder": 20
  },
  {
    "LibraryStoryGroupingId": 531,
    "EventQuestChapterId": 531,
    "SortOrder": 22
  },
  {
    "LibraryStoryGroupingId": 534,
    "EventQuestChapterId": 534,
    "SortOrder": 23
  },
  {
    "LibraryStoryGroupingId": 536,
    "EventQuestChapterId": 536,
    "SortOrder": 26
  },
  {
    "LibraryStoryGroupingId": 537,
    "EventQuestChapterId": 537,
    "SortOrder": 27
  },
  {
    "LibraryStoryGroupingId": 539,
    "EventQuestChapterId": 539,
    "SortOrder": 24
  },
  {
    "LibraryStoryGroupingId": 542,
    "EventQuestChapterId": 542,
    "SortOrder": 25
  },
  {
    "LibraryStoryGroupingId": 542,
    "EventQuestChapterId": 572,
    "SortOrder": 25
  },
  {
    "LibraryStoryGroupingId": 542,
    "EventQuestChapterId": 587,
    "SortOrder": 25
  },
  {
    "LibraryStoryGroupingId": 544,
    "EventQuestChapterId": 544,
    "SortOrder": 28
  },
  {
    "LibraryStoryGroupingId": 546,
    "EventQuestChapterId": 546,
    "SortOrder": 29
  },
  {
    "LibraryStoryGroupingId": 549,
    "EventQuestChapterId": 549,
    "SortOrder": 30
  },
  {
    "LibraryStoryGroupingId": 549,
    "EventQuestChapterId": 581,
    "SortOrder": 30
  },
  {
    "LibraryStoryGroupingId": 551,
    "EventQuestChapterId": 551,
    "SortOrder": 30
  },
  {
    "LibraryStoryGroupingId": 554,
    "EventQuestChapterId": 554,
    "SortOrder": 30
  },
  {
    "LibraryStoryGroupingId": 556,
    "EventQuestChapterId": 556,
    "SortOrder": 33
  },
  {
    "LibraryStoryGroupingId": 556,
    "EventQuestChapterId": 588,
    "SortOrder": 33
  },
  {
    "LibraryStoryGroupingId": 558,
    "EventQuestChapterId": 558,
    "SortOrder": 34
  },
  {
    "LibraryStoryGroupingId": 562,
    "EventQuestChapterId": 562,
    "SortOrder": 35
  },
  {
    "LibraryStoryGroupingId": 564,
    "EventQuestChapterId": 564,
    "SortOrder": 36
  },
  {
    "LibraryStoryGroupingId": 566,
    "EventQuestChapterId": 566,
    "SortOrder": 37
  },
  {
    "LibraryStoryGroupingId": 569,
    "EventQuestChapterId": 569,
    "SortOrder": 38
  },
  {
    "LibraryStoryGroupingId": 573,
    "EventQuestChapterId": 573,
    "SortOrder": 39
  },
  {
    "LibraryStoryGroupingId": 573,
    "EventQuestChapterId": 589,
    "SortOrder": 39
  },
  {
    "LibraryStoryGroupingId": 574,
    "EventQuestChapterId": 574,
    "SortOrder": 40
  },
  {
    "LibraryStoryGroupingId": 576,
    "EventQuestChapterId": 576,
    "SortOrder": 41
  },
  {
    "LibraryStoryGroupingId": 578,
    "EventQuestChapterId": 578,
    "SortOrder": 42
  },
  {
    "LibraryStoryGroupingId": 580,
    "EventQuestChapterId": 580,
    "SortOrder": 43
  },
  {
    "LibraryStoryGroupingId": 582,
    "EventQuestChapterId": 582,
    "SortOrder": 45
  },
  {
    "LibraryStoryGroupingId": 586,
    "EventQuestChapterId": 586,
    "SortOrder": 46
  }
]